nonechat/__init__.py
nonechat/app.py
nonechat/log_redirect.py
nonechat/message.py
nonechat/model.py
nonechat/setting.py
nonechat/utils.py
nonechat/backend/__init__.py
nonechat/backend/storage.py
nonechat/components/__init__.py
nonechat/components/action.py
nonechat/components/channel_selector.py
nonechat/components/footer.py
nonechat/components/header.py
nonechat/components/sidebar.py
nonechat/components/user_selector.py
nonechat/components/chatroom/__init__.py
nonechat/components/chatroom/history.py
nonechat/components/chatroom/input.py
nonechat/components/chatroom/message.py
nonechat/components/chatroom/toolbar.py
nonechat/components/log/__init__.py
nonechat/components/log/toolbar.py
nonechat/router/__init__.py
nonechat/router/router.py
nonechat/views/horizontal.py
nonechat/views/log_view.py
nonechat-0.6.0.dist-info/METADATA
nonechat-0.6.0.dist-info/WHEEL
nonechat-0.6.0.dist-info/top_level.txt
nonechat-0.6.0.dist-info/RECORD
