Metadata-Version: 2.4
Name: nonechat
Version: 0.6.0
Summary: Awesome chat console using Textual
Author-email: RF-Tar-Railt <rf_tar_railt@qq.com>
License: MIT
Project-URL: homepage, https://github.com/nonebot/nonechat
Project-URL: repository, https://github.com/nonebot/nonechat
Requires-Python: <4.0,>=3.9
Requires-Dist: textual<4.0.0,>=3.7.0
